chipiron/__init__.py
chipiron/py.typed
chipiron/data/players/board_evaluator_config/base_chipiron_board_eval.yaml
chipiron/data/players/board_evaluators/nn_pytorch/nn_pp2d2_2/base/architecture.yaml
chipiron/data/players/board_evaluators/nn_pytorch/nn_pp2d2_2/base/param.pt
chipiron/data/players/board_evaluators/nn_pytorch/nn_pp2d2_2_leaky/param_leaky/param.pt
chipiron/data/players/board_evaluators/nn_pytorch/nn_pp2d2_2_prelu/param_prelu/architecture.yaml
chipiron/data/players/board_evaluators/nn_pytorch/nn_pp2d2_2_prelu/param_prelu/param.pt
chipiron/data/players/board_evaluators/nn_pytorch/prelu_no_bug/architecture.yaml
chipiron/data/players/board_evaluators/nn_pytorch/prelu_no_bug/param.yaml
chipiron/data/players/board_evaluators/nn_pytorch/prelu_no_bug/param_multi_layer_perceptron_772_20_1_parametric_relu_hyperbolic_tangent_364_no_bug_player_to_move.pt
chipiron/data/players/player_config/Command_Line_Human.yaml
chipiron/data/players/player_config/Gui_Human.yaml
chipiron/data/players/player_config/Random.yaml
chipiron/data/players/player_config/RecurZipfBase3.yaml
chipiron/data/players/player_config/RecurZipfBase4.yaml
chipiron/data/players/player_config/RecurZipfSequool.yaml
chipiron/data/players/player_config/Sequool.yaml
chipiron/data/players/player_config/SequoolOnlyPromising.yaml
chipiron/data/players/player_config/SequoolOnlyPromisingRecur.yaml
chipiron/data/players/player_config/Stockfish.yaml
chipiron/data/players/player_config/Uniform.yaml
chipiron/data/players/player_config/UniformDepth.yaml
chipiron/data/players/player_config/UniformDepth2.yaml
chipiron/data/players/player_config/UniformDepth3.yaml
chipiron/data/players/player_config/Uniformbase.yaml
chipiron/data/players/player_config/chipiron/chipiron.yaml
chipiron/data/players/player_config/players_for_test_purposes/RecurZipfBase3.yaml
chipiron/data/players/player_config/players_for_test_purposes/RecurZipfBase4.yaml
chipiron/data/players/player_config/players_for_test_purposes/RecurZipfSequool.yaml
chipiron-0.1.9.dist-info/licenses/LICENSE
chipiron-0.1.9.dist-info/METADATA
chipiron-0.1.9.dist-info/WHEEL
chipiron-0.1.9.dist-info/top_level.txt
chipiron-0.1.9.dist-info/RECORD
