Metadata-Version: 2.4
Name: chipiron
Version: 0.1.9
Summary: chipiron plays chess
Author-email: Victor Gabillon <victorgabillon@gmail.com>
License-Expression: GPL-3.0-only
Project-URL: Homepage, https://github.com/victorgabillon/chipiron
Project-URL: Bug Tracker, https://github.com/victorgabillon/chipiron/issues
Keywords: chess,AI,torch
Classifier: Programming Language :: Python :: 3
Classifier: Operating System :: OS Independent
Requires-Python: >=3.12
License-File: LICENSE
Requires-Dist: PyYAML
Requires-Dist: PySide6==6.6.2
Requires-Dist: chess>=1.11.2
Requires-Dist: matplotlib>=3.8.2
Requires-Dist: sortedcollections>=2.1.0
Requires-Dist: pandas==2.2.0
Requires-Dist: numpy==1.26.0
Requires-Dist: torch>=2.2.2
Requires-Dist: torchinfo
Requires-Dist: numba>=0.59.0rc1
Requires-Dist: graphviz>=0.20.1
Requires-Dist: dacite>=1.9.2
Requires-Dist: customtkinter>=5.2
Requires-Dist: pyarrow
Requires-Dist: shakmaty_python_binding>=0.1.5
Requires-Dist: gprof2dot
Requires-Dist: mlflow
Requires-Dist: parsley_coco>=0.1.25
Requires-Dist: gdown
Dynamic: license-file
